proto/__init__.py
proto/_file_info.py
proto/_package_info.py
proto/datetime_helpers.py
proto/enums.py
proto/fields.py
proto/message.py
proto/modules.py
proto/primitives.py
proto/utils.py
proto/marshal/__init__.py
proto/marshal/compat.py
proto/marshal/marshal.py
proto/marshal/collections/__init__.py
proto/marshal/collections/maps.py
proto/marshal/collections/repeated.py
proto/marshal/rules/__init__.py
proto/marshal/rules/bytes.py
proto/marshal/rules/dates.py
proto/marshal/rules/enums.py
proto/marshal/rules/field_mask.py
proto/marshal/rules/message.py
proto/marshal/rules/stringy_numbers.py
proto/marshal/rules/struct.py
proto/marshal/rules/wrappers.py
proto_plus-1.22.3.dist-info/LICENSE
proto_plus-1.22.3.dist-info/METADATA
proto_plus-1.22.3.dist-info/WHEEL
proto_plus-1.22.3.dist-info/top_level.txt
proto_plus-1.22.3.dist-info/RECORD
